setup.py
jatt/__init__.py
jatt.egg-info/PKG-INFO
jatt.egg-info/SOURCES.txt
jatt.egg-info/dependency_links.txt
jatt.egg-info/not-zip-safe
jatt.egg-info/top_level.txt